nose/__init__.py
nose/__main__.py
nose/case.py
nose/commands.py
nose/config.py
nose/core.py
nose/exc.py
nose/failure.py
nose/importer.py
nose/inspector.py
nose/loader.py
nose/proxy.py
nose/pyversion.py
nose/result.py
nose/selector.py
nose/suite.py
nose/twistedtools.py
nose/usage.txt
nose/util.py
nose/ext/__init__.py
nose/ext/dtcompat.py
nose/plugins/__init__.py
nose/plugins/allmodules.py
nose/plugins/attrib.py
nose/plugins/base.py
nose/plugins/builtin.py
nose/plugins/capture.py
nose/plugins/collect.py
nose/plugins/cover.py
nose/plugins/debug.py
nose/plugins/deprecated.py
nose/plugins/doctests.py
nose/plugins/errorclass.py
nose/plugins/failuredetail.py
nose/plugins/isolate.py
nose/plugins/logcapture.py
nose/plugins/manager.py
nose/plugins/multiprocess.py
nose/plugins/plugintest.py
nose/plugins/prof.py
nose/plugins/skip.py
nose/plugins/testid.py
nose/plugins/xunit.py
nose/sphinx/__init__.py
nose/sphinx/pluginopts.py
nose/tools/__init__.py
nose/tools/nontrivial.py
nose/tools/trivial.py
nose_ng-1.4.3.data/data/share/man/man1/nosetests.1
nose_ng-1.4.3.dist-info/licenses/AUTHORS
nose_ng-1.4.3.dist-info/METADATA
nose_ng-1.4.3.dist-info/WHEEL
nose_ng-1.4.3.dist-info/entry_points.txt
nose_ng-1.4.3.dist-info/top_level.txt
nose_ng-1.4.3.dist-info/RECORD
