Metadata-Version: 2.4
Name: nose-ng
Version: 1.4.3
Summary: nose extends unittest to make testing easier
Author-email: Jason Pellerin <jpellerin+nose@gmail.com>
License: GNU LGPL
Project-URL: Homepage, https://nose.readthedocs.io/
Project-URL: Documentation, https://nose.readthedocs.io/
Project-URL: Repository, https://github.com/nose-devs/nose
Keywords: test,unittest,doctest,automatic,discovery
Classifier: Development Status :: 5 - Production/Stable
Classifier: Intended Audience :: Developers
Classifier: License :: OSI Approved :: GNU Library or Lesser General Public License (LGPL)
Classifier: Natural Language :: English
Classifier: Operating System :: OS Independent
Classifier: Programming Language :: Python
Classifier: Programming Language :: Python :: 3
Classifier: Programming Language :: Python :: 3.11
Classifier: Programming Language :: Python :: 3.12
Classifier: Programming Language :: Python :: 3.13
Classifier: Programming Language :: Python :: 3.14
Classifier: Topic :: Software Development :: Testing
Requires-Python: >=3.11
License-File: AUTHORS
Provides-Extra: dev
Requires-Dist: coverage; extra == "dev"
Requires-Dist: sphinx; extra == "dev"
Dynamic: license-file
